tltk/BEST.dict
tltk/PhSTrigram.sts
tltk/__init__.py
tltk/chkdeprc.py
tltk/chkgenre_rf.pklz
tltk/chklevel_rf.pklz
tltk/corpus.py
tltk/ner_tagger.pklz
tltk/nlp.py
tltk/pos_tagger.pklz
tltk/sent_segment.pklz
tltk/sylform_var.pklz
tltk/sylrule.lts
tltk/sylseg.3g
tltk/test.py
tltk/th2ipa.py
tltk/thaisyl.dict
tltk/thamalt.mco
tltk/thdict
tltk/word.pklz
tltk-1.10.dist-info/LICENSE-gpl.txt
tltk-1.10.dist-info/LICENSE.txt
tltk-1.10.dist-info/METADATA
tltk-1.10.dist-info/WHEEL
tltk-1.10.dist-info/entry_points.txt
tltk-1.10.dist-info/top_level.txt
tltk-1.10.dist-info/RECORD
