Metadata-Version: 2.1
Name: tltk
Version: 1.10
Summary: Thai Language Toolkit
Home-page: http://pypi.python.org/pypi/tltk/
Author: Wirote Aroonmanakun
Author-email: awirote@chula.ac.th
License: BSD-3-Clause
Keywords: Thai language toolkit,Thai language processing,segmentation,pos tag,transcription,romanization
Platform: UNKNOWN
Classifier: Development Status :: 5 - Production/Stable
Classifier: Intended Audience :: Developers
Classifier: Topic :: Text Processing :: Linguistic
Classifier: Topic :: Software Development :: Libraries :: Python Modules
Classifier: License :: OSI Approved :: BSD License
Classifier: Programming Language :: Python :: 3.8
License-File: LICENSE-gpl.txt
License-File: LICENSE.txt
Requires-Dist: nltk
Requires-Dist: scikit-learn
Requires-Dist: sklearn-crfsuite
Requires-Dist: gensim
